[
    [
        {
            "name": "d3-graphviz - npm",
            "href": "https://www.npmjs.com/package/d3-graphviz"
        },
        {
            "name": "GitHub - magjac/d3-graphviz: Graphviz DOT rendering and animated transitions using D3",
            "href": "https://github.com/magjac/d3-graphviz"
        },
        {
            "name": "Graphviz - Graph Visualization Software",
            "href": "http://www.graphviz.org/"
        },
        {
            "name": "The DOT Language",
            "href": "https://www.graphviz.org/doc/info/lang.html"
        }
    ]
]